interceptor/__init__.py
interceptor/interceptor_addon.py
interceptor/services/__init__.py
interceptor/services/detect_anonymize_pii_service.py
interceptor/services/detect_pii_gliner.py
interceptor/services/get_blocklist_service.py
interceptor/tools/__init__.py
interceptor/tools/compliance_report.py
interceptor/tools/detect_pii.py
interceptor/tools/detect_pii_remote.py
interceptor/tools/shadow_ai_detector.py
interceptor/tools/zt_log_forwarder.py
pii_detection/__init__.py
pii_detection/schema/__init__.py
pii_detection/schema/detect_anonymize_pii.py
pii_detection/services/__init__.py
pii_detection/services/detect_anonymize_pii_service.py
pii_detection/services/detect_pii_gliner.py
pii_detection/utils/__init__.py
pii_detection/utils/constants.py
zt_proxy.py
zt_proxy-0.1.3.dist-info/METADATA
zt_proxy-0.1.3.dist-info/WHEEL
zt_proxy-0.1.3.dist-info/RECORD
