Metadata-Version: 2.3
Name: zt-proxy
Version: 0.1.3
Summary: 
Author: Vijay Karavadra
Author-email: vijay.karavadra@zerotrusted.ai
Requires-Python: >=3.12,<3.13
Classifier: Programming Language :: Python :: 3
Classifier: Programming Language :: Python :: 3.12
Requires-Dist: aiofiles (>=24.1.0,<24.1.1)
Requires-Dist: beautifulsoup4 (>=4.13.4,<5.0.0)
Requires-Dist: bs4 (>=0.0.2,<0.0.3)
Requires-Dist: faker (>=25.2.0)
Requires-Dist: gliner (>=0.2.5,<0.3.0)
Requires-Dist: httpx (>=0.28.1,<0.29.0)
Requires-Dist: loguru (>=0.7.3,<0.8.0)
Requires-Dist: lxml (>=6.0.0,<7.0.0)
Requires-Dist: mitmproxy (>=12.1.1,<13.0.0)
Requires-Dist: openai (>=1.98.0,<2.0.0)
Requires-Dist: pandas (>=2.3.1,<3.0.0)
Requires-Dist: presidio-analyzer (>=2.2.354,<2.2.355)
Requires-Dist: pymupdf (>=1.24.10,<1.24.11)
Requires-Dist: requests
